{
  "カードの種類": "Pokémon",
  "カード番号": [
    "a4#80"
  ],
  "名前": "Togekiss",
  "レア度": {
    "rarity_types": [
      "diamond"
    ],
    "count": 3
  },
  "HP": "140",
  "タイプ": "psychic",
  "弱点": "metal +20",
  "にげる": 1,
  "説明文": "These Pokémon are never seen anywhere near conflict or turmoil. In recent times, they’ve hardly been seen at all.",
  "イラストレーター": "sui",
  "収録セット": [
    "Wisdom of Sea and Sky"
  ],
  "入手方法": [
    "パック: Ho-Oh Pack",
    "パック開封ポイント: 150"
  ],
  "進化ステージ": "Stage 2",
  "特別ルール": null,
  "エフェクト一覧": [
    "Sparkles_Flair_Gold_Cosmetic.webp",
    "Twinkles_Flair_Purple_Cosmetic.webp",
    "Heart_Outlines_Flair_Pink_Battle.webp",
    "Sunshine_Sparkles_Flair_Purple_Battle.webp"
  ],
  "特性": [
    {
      "特性名": "Celestial Blessing",
      "効果": "If any damage is done to this Pokémon by attacks, flip a coin. If heads, prevent that damage."
    }
  ],
  "ワザ": [
    {
      "名前": "Magical Shot",
      "ダメージ": "70",
      "効果": "N/A",
      "エネルギーコスト": 3,
      "エネルギータイプ": [
        "psychic",
        "colorless",
        "colorless"
      ]
    }
  ],
  "Alternate Arts": [],
  "進化先": {},
  "進化前": {
    "0": [
      [
        "Stage 1",
        "Togetic"
      ]
    ]
  }
}