{
  "カードの種類": "Pokémon",
  "カード番号": [
    "a1#69"
  ],
  "名前": "Kingler",
  "レア度": {
    "rarity_types": [
      "diamond"
    ],
    "count": 2
  },
  "HP": "120",
  "タイプ": "water",
  "弱点": "lightning +20",
  "にげる": 3,
  "説明文": "Its large and hard pincer has 10,000-horsepower strength. However, being so big, it is unwieldy to move.",
  "イラストレーター": "Shigenori Negishi",
  "収録セット": [
    "Genetic Apex"
  ],
  "入手方法": [
    "パック: Mewtwo Pack",
    "パック開封ポイント: 70"
  ],
  "進化ステージ": "Stage 1",
  "特別ルール": null,
  "エフェクト一覧": [
    "Sparkles_Flair_Gold_Cosmetic.webp",
    "Mini_Triangles_Flair_Blue_Battle.webp",
    "Poké_Ball_Flair_Cosmetic.webp",
    "Tiny_Twinkles_Flair_Blue_Battle.webp"
  ],
  "特性": [],
  "ワザ": [
    {
      "名前": "KO Crab",
      "ダメージ": "80+",
      "効果": "Flip 2 coins. If both of them are heads, this attack does 80 more damage.",
      "エネルギーコスト": 3,
      "エネルギータイプ": [
        "water",
        "water",
        "colorless"
      ]
    }
  ],
  "Alternate Arts": [
    {
      "カード番号": "a4a#96"
    }
  ],
  "進化先": {},
  "進化前": {
    "0": [
      [
        "Basic",
        "Krabby"
      ]
    ]
  }
}