{
  "カードの種類": "Pokémon",
  "カード番号": [
    "promo-a#30"
  ],
  "名前": "Eevee",
  "レア度": {
    "rarity_types": [
      "diamond"
    ],
    "count": 1
  },
  "HP": "60",
  "タイプ": "colorless",
  "弱点": "fighting +20",
  "にげる": 1,
  "説明文": "Its ability to evolve into many forms allows it to adapt smoothly and perfectly to any environment.",
  "イラストレーター": "En Morikura",
  "収録セット": [
    "Promo A"
  ],
  "入手方法": [
    "イベント: Blastoise drop event"
  ],
  "進化ステージ": "Basic",
  "特別ルール": null,
  "エフェクト一覧": [
    "Sparkles_Flair_Gold_Cosmetic.webp",
    "Small_Hearts_Flair_Pink_Cosmetic.webp",
    "Petals_Flair_Red_Cosmetic.webp",
    "Star_Outlines_Flair_Yellow_Battle.webp"
  ],
  "特性": [],
  "ワザ": [
    {
      "名前": "Growl",
      "ダメージ": "N/A",
      "効果": "During your opponent’s next turn, attacks used by the Defending Pokémon do −20 damage.",
      "エネルギーコスト": 1,
      "エネルギータイプ": [
        "colorless"
      ]
    }
  ],
  "Alternate Arts": [],
  "進化先": {
    "0": [
      [
        "Stage 1",
        "Flareon ex,                                         Espeon ex,                                         Vaporeon,                                         Umbreon ex,                                         Leafeon,                                         Sylveon,                                         Sylveon ex,                                         Leafeon ex,                                         Glaceon,                                         Flareon,                                         Jolteon,                                         Jolteon ex,                                         Glaceon ex,                                         Umbreon,                                         Espeon"
      ]
    ]
  },
  "進化前": {}
}