{
  "カードの種類": "Pokémon",
  "カード番号": [
    "a1#101"
  ],
  "名前": "Electabuzz",
  "レア度": {
    "rarity_types": [
      "diamond"
    ],
    "count": 1
  },
  "HP": "70",
  "タイプ": "lightning",
  "弱点": "fighting +20",
  "にげる": 1,
  "説明文": "Many power plants keep Ground-type Pokémon around as a defense against Electabuzz that come seeking electricity.",
  "イラストレーター": "Ryuta Fuse",
  "収録セット": [
    "Genetic Apex"
  ],
  "入手方法": [
    "パック: Pikachu Pack",
    "パック開封ポイント: 35"
  ],
  "進化ステージ": "Basic",
  "特別ルール": null,
  "エフェクト一覧": [
    "Sparkles_Flair_Gold_Cosmetic.webp",
    "Lightning_Energy_Flair_Cosmetic.webp",
    "Lightning_Surge_Flair_Yellow_Cosmetic.webp",
    "Lightning_Surge_Flair_Yellow_Battle.webp"
  ],
  "特性": [],
  "ワザ": [
    {
      "名前": "Thunder Punch",
      "ダメージ": "40+",
      "効果": "Flip a coin. If heads, this attack does 40 more damage. If tails, this Pokémon also does 20 damage to itself.",
      "エネルギーコスト": 2,
      "エネルギータイプ": [
        "lightning",
        "lightning"
      ]
    }
  ],
  "Alternate Arts": [],
  "進化先": {
    "0": [
      [
        "Stage 1",
        "Electivire"
      ]
    ]
  },
  "進化前": {}
}