{
  "カードの種類": "Pokémon",
  "カード番号": [
    "a3b#76"
  ],
  "名前": "Sylveon",
  "レア度": {
    "rarity_types": [
      "star"
    ],
    "count": 1
  },
  "HP": "90",
  "タイプ": "psychic",
  "弱点": "metal +20",
  "にげる": 1,
  "説明文": "This Pokémon uses its ribbonlike feelers to send a soothing aura into its opponents, erasing their hostility.",
  "イラストレーター": "saino misaki",
  "収録セット": [
    "Eevee Grove"
  ],
  "入手方法": [
    "パック: Eevee Grove",
    "パック開封ポイント: 400"
  ],
  "進化ステージ": "Stage 1",
  "特別ルール": null,
  "エフェクト一覧": [
    "Tiny_Twinkles_Flair_Yellow_Battle.webp",
    "Petals_Flair_Red_Battle.webp",
    "Heart_Outlines_Flair_Pink_Battle.webp",
    "Music_Notes_Flair_Pink_Battle.webp"
  ],
  "特性": [],
  "ワザ": [
    {
      "名前": "Evoharmony",
      "ダメージ": "40+",
      "効果": "This attack does 30 more damage for each Evolution Pokémon on your Bench.",
      "エネルギーコスト": 2,
      "エネルギータイプ": [
        "psychic",
        "colorless"
      ]
    }
  ],
  "Alternate Arts": [
    {
      "カード番号": "a3b#33"
    }
  ],
  "進化先": {},
  "進化前": {
    "0": [
      [
        "Basic",
        "Eevee"
      ]
    ]
  }
}