{
  "url": "https://www.pokemon-zone.com/events/eevee-mass-outbreak-event/",
  "title": "Eevee Mass Outbreak Wonder Pick Event",
  "period": {
    "text": "Jul 21 - Jul 30",
    "start_date": "2025-07-21",
    "end_date": "2025-07-30"
  },
  "target_type": "",
  "bonus_picks": [
    {
      "type": "bonus",
      "percent": 9,
      "items": [
        {
          "type": "card",
          "name": "Eevee Common",
          "full_name": "Eevee Common - Genetic Apex (A1) #208",
          "url": "/cards/a1/208/eevee/",
          "id": "a1/208"
        },
        {
          "type": "card",
          "name": "Eevee Common",
          "full_name": "Eevee Common - Mythical Island (A1a) #61",
          "url": "/cards/a1a/61/eevee/",
          "id": "a1a/61"
        },
        {
          "type": "card",
          "name": "Eevee Common",
          "full_name": "Eevee Common - Space-Time Smackdown (A2) #126",
          "url": "/cards/a2/126/eevee/",
          "id": "a2/126"
        },
        {
          "type": "card",
          "name": "Vaporeon Rare",
          "full_name": "Vaporeon Rare - Eevee Grove (A3b) #16",
          "url": "/cards/a3b/16/vaporeon/",
          "id": "a3b/16"
        },
        {
          "type": "card",
          "name": "Eevee Bag Uncommon",
          "full_name": "Eevee Bag Uncommon - Eevee Grove (A3b) #66",
          "url": "/cards/a3b/66/eevee-bag/",
          "id": "a3b/66"
        }
      ],
      "cost": 0,
      "cost_free": true
    },
    {
      "type": "bonus",
      "percent": 9,
      "items": [
        {
          "type": "card",
          "name": "Eevee Common",
          "full_name": "Eevee Common - Triumphant Light (A2a) #62",
          "url": "/cards/a2a/62/eevee/",
          "id": "a2a/62"
        },
        {
          "type": "card",
          "name": "Eevee Common",
          "full_name": "Eevee Common - Eevee Grove (A3b) #55",
          "url": "/cards/a3b/55/eevee/",
          "id": "a3b/55"
        },
        {
          "type": "card",
          "name": "Eevee Common",
          "full_name": "Eevee Common - Space-Time Smackdown (A2) #126",
          "url": "/cards/a2/126/eevee/",
          "id": "a2/126"
        },
        {
          "type": "card",
          "name": "Leafeon Rare",
          "full_name": "Leafeon Rare - Eevee Grove (A3b) #2",
          "url": "/cards/a3b/2/leafeon/",
          "id": "a3b/2"
        },
        {
          "type": "card",
          "name": "Eevee Bag Uncommon",
          "full_name": "Eevee Bag Uncommon - Eevee Grove (A3b) #66",
          "url": "/cards/a3b/66/eevee-bag/",
          "id": "a3b/66"
        }
      ],
      "cost": 0,
      "cost_free": true
    },
    {
      "type": "bonus",
      "percent": 9,
      "items": [
        {
          "type": "card",
          "name": "Eevee Common",
          "full_name": "Eevee Common - Mythical Island (A1a) #61",
          "url": "/cards/a1a/61/eevee/",
          "id": "a1a/61"
        },
        {
          "type": "card",
          "name": "Eevee Common",
          "full_name": "Eevee Common - Space-Time Smackdown (A2) #126",
          "url": "/cards/a2/126/eevee/",
          "id": "a2/126"
        },
        {
          "type": "card",
          "name": "Eevee Common",
          "full_name": "Eevee Common - Triumphant Light (A2a) #62",
          "url": "/cards/a2a/62/eevee/",
          "id": "a2a/62"
        },
        {
          "type": "card",
          "name": "Umbreon Rare",
          "full_name": "Umbreon Rare - Eevee Grove (A3b) #43",
          "url": "/cards/a3b/43/umbreon/",
          "id": "a3b/43"
        },
        {
          "type": "card",
          "name": "Eevee Bag Uncommon",
          "full_name": "Eevee Bag Uncommon - Eevee Grove (A3b) #66",
          "url": "/cards/a3b/66/eevee-bag/",
          "id": "a3b/66"
        }
      ],
      "cost": 0,
      "cost_free": true
    },
    {
      "type": "bonus",
      "percent": 9,
      "items": [
        {
          "type": "card",
          "name": "Eevee Common",
          "full_name": "Eevee Common - Space-Time Smackdown (A2) #126",
          "url": "/cards/a2/126/eevee/",
          "id": "a2/126"
        },
        {
          "type": "card",
          "name": "Eevee Common",
          "full_name": "Eevee Common - Triumphant Light (A2a) #62",
          "url": "/cards/a2a/62/eevee/",
          "id": "a2a/62"
        },
        {
          "type": "card",
          "name": "Eevee Common",
          "full_name": "Eevee Common - Eevee Grove (A3b) #55",
          "url": "/cards/a3b/55/eevee/",
          "id": "a3b/55"
        },
        {
          "type": "card",
          "name": "Espeon Rare",
          "full_name": "Espeon Rare - Eevee Grove (A3b) #28",
          "url": "/cards/a3b/28/espeon/",
          "id": "a3b/28"
        },
        {
          "type": "card",
          "name": "Eevee Bag Uncommon",
          "full_name": "Eevee Bag Uncommon - Eevee Grove (A3b) #66",
          "url": "/cards/a3b/66/eevee-bag/",
          "id": "a3b/66"
        }
      ],
      "cost": 0,
      "cost_free": true
    },
    {
      "type": "bonus",
      "percent": 9,
      "items": [
        {
          "type": "item",
          "name": "Shop ticket",
          "image_url": "https://assets.pokemon-zone.com/game-assets/UI/Textures/System/ItemIcons/Currency/SHOPTICKET.webp",
          "count": "1"
        },
        {
          "type": "item",
          "name": "Wonder Hourglass",
          "image_url": "https://assets.pokemon-zone.com/game-assets/UI/Textures/System/ItemIcons/ChallengePowerCharger/CHALLENGE_CHARGER_110030.webp",
          "count": "1"
        },
        {
          "type": "item",
          "name": "Pack Hourglass",
          "image_url": "https://assets.pokemon-zone.com/game-assets/UI/Textures/System/ItemIcons/PackPowerCharger/PACK_CHARGER_100030.webp",
          "count": "1"
        },
        {
          "type": "card",
          "name": "Eevee Common",
          "full_name": "Eevee Common - Genetic Apex (A1) #208",
          "url": "/cards/a1/208/eevee/",
          "id": "a1/208"
        },
        {
          "type": "card",
          "name": "Eevee Bag Uncommon",
          "full_name": "Eevee Bag Uncommon - Eevee Grove (A3b) #66",
          "url": "/cards/a3b/66/eevee-bag/",
          "id": "a3b/66"
        }
      ],
      "cost": 0,
      "cost_free": true
    },
    {
      "type": "bonus",
      "percent": 9,
      "items": [
        {
          "type": "card",
          "name": "Eevee Common",
          "full_name": "Eevee Common - Genetic Apex (A1) #206",
          "url": "/cards/a1/206/eevee/",
          "id": "a1/206"
        },
        {
          "type": "card",
          "name": "Eevee Common",
          "full_name": "Eevee Common - Genetic Apex (A1) #207",
          "url": "/cards/a1/207/eevee/",
          "id": "a1/207"
        },
        {
          "type": "card",
          "name": "Eevee Common",
          "full_name": "Eevee Common - Genetic Apex (A1) #208",
          "url": "/cards/a1/208/eevee/",
          "id": "a1/208"
        },
        {
          "type": "card",
          "name": "Flareon Rare",
          "full_name": "Flareon Rare - Eevee Grove (A3b) #8",
          "url": "/cards/a3b/8/flareon/",
          "id": "a3b/8"
        },
        {
          "type": "card",
          "name": "Eevee Bag Uncommon",
          "full_name": "Eevee Bag Uncommon - Eevee Grove (A3b) #66",
          "url": "/cards/a3b/66/eevee-bag/",
          "id": "a3b/66"
        }
      ],
      "cost": 0,
      "cost_free": true
    },
    {
      "type": "bonus",
      "percent": 9,
      "items": [
        {
          "type": "card",
          "name": "Eevee Common",
          "full_name": "Eevee Common - Eevee Grove (A3b) #55",
          "url": "/cards/a3b/55/eevee/",
          "id": "a3b/55"
        },
        {
          "type": "card",
          "name": "Eevee Common",
          "full_name": "Eevee Common - Genetic Apex (A1) #206",
          "url": "/cards/a1/206/eevee/",
          "id": "a1/206"
        },
        {
          "type": "card",
          "name": "Eevee Common",
          "full_name": "Eevee Common - Genetic Apex (A1) #207",
          "url": "/cards/a1/207/eevee/",
          "id": "a1/207"
        },
        {
          "type": "card",
          "name": "Sylveon Rare",
          "full_name": "Sylveon Rare - Eevee Grove (A3b) #33",
          "url": "/cards/a3b/33/sylveon/",
          "id": "a3b/33"
        },
        {
          "type": "card",
          "name": "Eevee Bag Uncommon",
          "full_name": "Eevee Bag Uncommon - Eevee Grove (A3b) #66",
          "url": "/cards/a3b/66/eevee-bag/",
          "id": "a3b/66"
        }
      ],
      "cost": 0,
      "cost_free": true
    },
    {
      "type": "bonus",
      "percent": 9,
      "items": [
        {
          "type": "item",
          "name": "Shop ticket",
          "image_url": "https://assets.pokemon-zone.com/game-assets/UI/Textures/System/ItemIcons/Currency/SHOPTICKET.webp",
          "count": "1"
        },
        {
          "type": "item",
          "name": "Wonder Hourglass",
          "image_url": "https://assets.pokemon-zone.com/game-assets/UI/Textures/System/ItemIcons/ChallengePowerCharger/CHALLENGE_CHARGER_110030.webp",
          "count": "1"
        },
        {
          "type": "item",
          "name": "Pack Hourglass",
          "image_url": "https://assets.pokemon-zone.com/game-assets/UI/Textures/System/ItemIcons/PackPowerCharger/PACK_CHARGER_100030.webp",
          "count": "1"
        },
        {
          "type": "card",
          "name": "Eevee Common",
          "full_name": "Eevee Common - Genetic Apex (A1) #206",
          "url": "/cards/a1/206/eevee/",
          "id": "a1/206"
        },
        {
          "type": "card",
          "name": "Eevee Bag Uncommon",
          "full_name": "Eevee Bag Uncommon - Eevee Grove (A3b) #66",
          "url": "/cards/a3b/66/eevee-bag/",
          "id": "a3b/66"
        }
      ],
      "cost": 0,
      "cost_free": true
    },
    {
      "type": "bonus",
      "percent": 9,
      "items": [
        {
          "type": "card",
          "name": "Eevee Common",
          "full_name": "Eevee Common - Genetic Apex (A1) #207",
          "url": "/cards/a1/207/eevee/",
          "id": "a1/207"
        },
        {
          "type": "card",
          "name": "Eevee Common",
          "full_name": "Eevee Common - Genetic Apex (A1) #208",
          "url": "/cards/a1/208/eevee/",
          "id": "a1/208"
        },
        {
          "type": "card",
          "name": "Eevee Common",
          "full_name": "Eevee Common - Mythical Island (A1a) #61",
          "url": "/cards/a1a/61/eevee/",
          "id": "a1a/61"
        },
        {
          "type": "card",
          "name": "Jolteon Rare",
          "full_name": "Jolteon Rare - Eevee Grove (A3b) #25",
          "url": "/cards/a3b/25/jolteon/",
          "id": "a3b/25"
        },
        {
          "type": "card",
          "name": "Eevee Bag Uncommon",
          "full_name": "Eevee Bag Uncommon - Eevee Grove (A3b) #66",
          "url": "/cards/a3b/66/eevee-bag/",
          "id": "a3b/66"
        }
      ],
      "cost": 0,
      "cost_free": true
    },
    {
      "type": "bonus",
      "percent": 9,
      "items": [
        {
          "type": "card",
          "name": "Eevee Common",
          "full_name": "Eevee Common - Eevee Grove (A3b) #55",
          "url": "/cards/a3b/55/eevee/",
          "id": "a3b/55"
        },
        {
          "type": "card",
          "name": "Eevee Common",
          "full_name": "Eevee Common - Mythical Island (A1a) #61",
          "url": "/cards/a1a/61/eevee/",
          "id": "a1a/61"
        },
        {
          "type": "card",
          "name": "Eevee Common",
          "full_name": "Eevee Common - Genetic Apex (A1) #206",
          "url": "/cards/a1/206/eevee/",
          "id": "a1/206"
        },
        {
          "type": "card",
          "name": "Glaceon Rare",
          "full_name": "Glaceon Rare - Eevee Grove (A3b) #17",
          "url": "/cards/a3b/17/glaceon/",
          "id": "a3b/17"
        },
        {
          "type": "card",
          "name": "Eevee Bag Uncommon",
          "full_name": "Eevee Bag Uncommon - Eevee Grove (A3b) #66",
          "url": "/cards/a3b/66/eevee-bag/",
          "id": "a3b/66"
        }
      ],
      "cost": 0,
      "cost_free": true
    },
    {
      "type": "bonus",
      "percent": 9,
      "items": [
        {
          "type": "item",
          "name": "Shop ticket",
          "image_url": "https://assets.pokemon-zone.com/game-assets/UI/Textures/System/ItemIcons/Currency/SHOPTICKET.webp",
          "count": "1"
        },
        {
          "type": "item",
          "name": "Wonder Hourglass",
          "image_url": "https://assets.pokemon-zone.com/game-assets/UI/Textures/System/ItemIcons/ChallengePowerCharger/CHALLENGE_CHARGER_110030.webp",
          "count": "1"
        },
        {
          "type": "item",
          "name": "Pack Hourglass",
          "image_url": "https://assets.pokemon-zone.com/game-assets/UI/Textures/System/ItemIcons/PackPowerCharger/PACK_CHARGER_100030.webp",
          "count": "1"
        },
        {
          "type": "card",
          "name": "Eevee Common",
          "full_name": "Eevee Common - Genetic Apex (A1) #207",
          "url": "/cards/a1/207/eevee/",
          "id": "a1/207"
        },
        {
          "type": "card",
          "name": "Eevee Bag Uncommon",
          "full_name": "Eevee Bag Uncommon - Eevee Grove (A3b) #66",
          "url": "/cards/a3b/66/eevee-bag/",
          "id": "a3b/66"
        }
      ],
      "cost": 0,
      "cost_free": true
    }
  ],
  "rare_picks": [
    {
      "type": "rare",
      "percent": 25,
      "items": [
        {
          "type": "card",
          "name": "Eevee ex Double Rare",
          "full_name": "Eevee ex Double Rare - Eevee Grove (A3b) #56",
          "url": "/cards/a3b/56/eevee-ex/",
          "id": "a3b/56"
        },
        {
          "type": "card",
          "name": "Flareon ex Double Rare",
          "full_name": "Flareon ex Double Rare - Eevee Grove (A3b) #9",
          "url": "/cards/a3b/9/flareon-ex/",
          "id": "a3b/9"
        },
        {
          "type": "card",
          "name": "Flareon Rare",
          "full_name": "Flareon Rare - Eevee Grove (A3b) #8",
          "url": "/cards/a3b/8/flareon/",
          "id": "a3b/8"
        },
        {
          "type": "card",
          "name": "Jolteon Rare",
          "full_name": "Jolteon Rare - Eevee Grove (A3b) #25",
          "url": "/cards/a3b/25/jolteon/",
          "id": "a3b/25"
        },
        {
          "type": "card",
          "name": "Umbreon Rare",
          "full_name": "Umbreon Rare - Eevee Grove (A3b) #43",
          "url": "/cards/a3b/43/umbreon/",
          "id": "a3b/43"
        }
      ],
      "cost": 3,
      "cost_free": false
    },
    {
      "type": "rare",
      "percent": 25,
      "items": [
        {
          "type": "card",
          "name": "Eevee ex Double Rare",
          "full_name": "Eevee ex Double Rare - Eevee Grove (A3b) #56",
          "url": "/cards/a3b/56/eevee-ex/",
          "id": "a3b/56"
        },
        {
          "type": "card",
          "name": "Leafeon ex Double Rare",
          "full_name": "Leafeon ex Double Rare - Triumphant Light (A2a) #10",
          "url": "/cards/a2a/10/leafeon-ex/",
          "id": "a2a/10"
        },
        {
          "type": "card",
          "name": "Leafeon Rare",
          "full_name": "Leafeon Rare - Eevee Grove (A3b) #2",
          "url": "/cards/a3b/2/leafeon/",
          "id": "a3b/2"
        },
        {
          "type": "card",
          "name": "Vaporeon Rare",
          "full_name": "Vaporeon Rare - Eevee Grove (A3b) #16",
          "url": "/cards/a3b/16/vaporeon/",
          "id": "a3b/16"
        },
        {
          "type": "card",
          "name": "Espeon Rare",
          "full_name": "Espeon Rare - Eevee Grove (A3b) #28",
          "url": "/cards/a3b/28/espeon/",
          "id": "a3b/28"
        }
      ],
      "cost": 3,
      "cost_free": false
    },
    {
      "type": "rare",
      "percent": 25,
      "items": [
        {
          "type": "card",
          "name": "Eevee ex Double Rare",
          "full_name": "Eevee ex Double Rare - Eevee Grove (A3b) #56",
          "url": "/cards/a3b/56/eevee-ex/",
          "id": "a3b/56"
        },
        {
          "type": "card",
          "name": "Glaceon ex Double Rare",
          "full_name": "Glaceon ex Double Rare - Triumphant Light (A2a) #22",
          "url": "/cards/a2a/22/glaceon-ex/",
          "id": "a2a/22"
        },
        {
          "type": "card",
          "name": "Glaceon Rare",
          "full_name": "Glaceon Rare - Eevee Grove (A3b) #17",
          "url": "/cards/a3b/17/glaceon/",
          "id": "a3b/17"
        },
        {
          "type": "card",
          "name": "Umbreon Rare",
          "full_name": "Umbreon Rare - Eevee Grove (A3b) #43",
          "url": "/cards/a3b/43/umbreon/",
          "id": "a3b/43"
        },
        {
          "type": "card",
          "name": "Jolteon Rare",
          "full_name": "Jolteon Rare - Eevee Grove (A3b) #25",
          "url": "/cards/a3b/25/jolteon/",
          "id": "a3b/25"
        }
      ],
      "cost": 3,
      "cost_free": false
    },
    {
      "type": "rare",
      "percent": 25,
      "items": [
        {
          "type": "card",
          "name": "Eevee ex Double Rare",
          "full_name": "Eevee ex Double Rare - Eevee Grove (A3b) #56",
          "url": "/cards/a3b/56/eevee-ex/",
          "id": "a3b/56"
        },
        {
          "type": "card",
          "name": "Sylveon ex Double Rare",
          "full_name": "Sylveon ex Double Rare - Deluxe Pack: ex (A4b) #177",
          "url": "/cards/a4b/177/sylveon-ex/",
          "id": "a4b/177"
        },
        {
          "type": "card",
          "name": "Sylveon Rare",
          "full_name": "Sylveon Rare - Eevee Grove (A3b) #33",
          "url": "/cards/a3b/33/sylveon/",
          "id": "a3b/33"
        },
        {
          "type": "card",
          "name": "Espeon Rare",
          "full_name": "Espeon Rare - Eevee Grove (A3b) #28",
          "url": "/cards/a3b/28/espeon/",
          "id": "a3b/28"
        },
        {
          "type": "card",
          "name": "Vaporeon Rare",
          "full_name": "Vaporeon Rare - Eevee Grove (A3b) #16",
          "url": "/cards/a3b/16/vaporeon/",
          "id": "a3b/16"
        }
      ],
      "cost": 3,
      "cost_free": false
    }
  ],
  "exclusive_flair": [],
  "missions": [
    {
      "name": "Eevee Mass Outbreak Event",
      "period": "Jul 21 - Jul 30, 2025",
      "missions": [
        {
          "description": "Collect 1 Eevee card",
          "rewards": [
            {
              "name": "1x Shop ticket",
              "local_file": "Shop ticket.webp",
              "url": "https://assets.pokemon-zone.com/game-assets/UI/Textures/System/ItemIcons/Currency/SHOPTICKET.webp",
              "amount": "1",
              "type": "main"
            },
            {
              "name": "1x Wonder Hourglass",
              "local_file": null,
              "url": "https://assets.pokemon-zone.com/game-assets/UI/Textures/System/ItemIcons/ChallengePowerCharger/CHALLENGE_CHARGER_110030.webp",
              "amount": "1",
              "type": "sub"
            }
          ],
          "target": "0/1"
        },
        {
          "description": "Collect 3 Eevee cards",
          "rewards": [
            {
              "name": "1x Eevee",
              "local_file": null,
              "url": "https://assets.pokemon-zone.com/game-assets/CardPreviews/cPK_90_002060_00_EIEVUI_R.webp",
              "amount": "1",
              "type": "main"
            }
          ],
          "target": "0/3"
        },
        {
          "description": "Collect 1 Eevee ex card",
          "rewards": [
            {
              "name": "1x Shop ticket",
              "local_file": "Shop ticket.webp",
              "url": "https://assets.pokemon-zone.com/game-assets/UI/Textures/System/ItemIcons/Currency/SHOPTICKET.webp",
              "amount": "1",
              "type": "main"
            },
            {
              "name": "1x Wonder Hourglass",
              "local_file": null,
              "url": "https://assets.pokemon-zone.com/game-assets/UI/Textures/System/ItemIcons/ChallengePowerCharger/CHALLENGE_CHARGER_110030.webp",
              "amount": "1",
              "type": "sub"
            }
          ],
          "target": "0/1"
        },
        {
          "description": "Wonder pick 3 times",
          "rewards": [
            {
              "name": "1x Shop ticket",
              "local_file": "Shop ticket.webp",
              "url": "https://assets.pokemon-zone.com/game-assets/UI/Textures/System/ItemIcons/Currency/SHOPTICKET.webp",
              "amount": "1",
              "type": "main"
            },
            {
              "name": "1x Wonder Hourglass",
              "local_file": null,
              "url": "https://assets.pokemon-zone.com/game-assets/UI/Textures/System/ItemIcons/ChallengePowerCharger/CHALLENGE_CHARGER_110030.webp",
              "amount": "1",
              "type": "sub"
            }
          ],
          "target": "0/3"
        },
        {
          "description": "Wonder pick 5 times",
          "rewards": [
            {
              "name": "3x Shop ticket",
              "local_file": "Shop ticket.webp",
              "url": "https://assets.pokemon-zone.com/game-assets/UI/Textures/System/ItemIcons/Currency/SHOPTICKET.webp",
              "amount": "3",
              "type": "main"
            },
            {
              "name": "3x Wonder Hourglass",
              "local_file": null,
              "url": "https://assets.pokemon-zone.com/game-assets/UI/Textures/System/ItemIcons/ChallengePowerCharger/CHALLENGE_CHARGER_110030.webp",
              "amount": "3",
              "type": "sub"
            }
          ],
          "target": "0/5"
        },
        {
          "description": "Collect 5 Colorless cards",
          "rewards": [
            {
              "name": "3x Shop ticket",
              "local_file": "Shop ticket.webp",
              "url": "https://assets.pokemon-zone.com/game-assets/UI/Textures/System/ItemIcons/Currency/SHOPTICKET.webp",
              "amount": "3",
              "type": "main"
            },
            {
              "name": "2x Wonder Hourglass",
              "local_file": null,
              "url": "https://assets.pokemon-zone.com/game-assets/UI/Textures/System/ItemIcons/ChallengePowerCharger/CHALLENGE_CHARGER_110030.webp",
              "amount": "2",
              "type": "sub"
            }
          ],
          "target": "0/5"
        },
        {
          "description": "Collect 10 Colorless cards",
          "rewards": [
            {
              "name": "5x Shop ticket",
              "local_file": "Shop ticket.webp",
              "url": "https://assets.pokemon-zone.com/game-assets/UI/Textures/System/ItemIcons/Currency/SHOPTICKET.webp",
              "amount": "5",
              "type": "main"
            },
            {
              "name": "3x Wonder Hourglass",
              "local_file": null,
              "url": "https://assets.pokemon-zone.com/game-assets/UI/Textures/System/ItemIcons/ChallengePowerCharger/CHALLENGE_CHARGER_110030.webp",
              "amount": "3",
              "type": "sub"
            }
          ],
          "target": "0/10"
        },
        {
          "description": "Collect 15 Colorless cards",
          "rewards": [
            {
              "name": "7x Shop ticket",
              "local_file": "Shop ticket.webp",
              "url": "https://assets.pokemon-zone.com/game-assets/UI/Textures/System/ItemIcons/Currency/SHOPTICKET.webp",
              "amount": "7",
              "type": "main"
            },
            {
              "name": "4x Wonder Hourglass",
              "local_file": null,
              "url": "https://assets.pokemon-zone.com/game-assets/UI/Textures/System/ItemIcons/ChallengePowerCharger/CHALLENGE_CHARGER_110030.webp",
              "amount": "4",
              "type": "sub"
            }
          ],
          "target": "0/15"
        }
      ]
    }
  ]
}