{
  "カードの種類": "Pokémon",
  "カード番号": [
    "a3a#45"
  ],
  "名前": "Naganadel",
  "レア度": {
    "rarity_types": [
      "diamond"
    ],
    "count": 3
  },
  "HP": "100",
  "タイプ": "darkness",
  "弱点": "fighting +20",
  "にげる": 2,
  "説明文": "It stores hundreds of liters of poisonous liquid inside its body. It is one of the organisms known as UBs.",
  "イラストレーター": "Shin Nagasawa",
  "収録セット": [
    "Extradimensional Crisis"
  ],
  "入手方法": [
    "パック: Extradimensional Crisis",
    "イベント: Rare Pick - Ultra Beast Mass Outbreak Event",
    "パック開封ポイント: 150"
  ],
  "進化ステージ": "Stage 1",
  "特別ルール": [
    "Ultra Beast"
  ],
  "エフェクト一覧": [
    "Ultra_Beast_Flair_Cosmetic.webp",
    "Twinkles_Flair_Blue_Cosmetic.webp",
    "Ultra_Beast_Flair_Battle.webp",
    "Sword_Flash_Flair_Light_blue_Battle.webp"
  ],
  "特性": [],
  "ワザ": [
    {
      "名前": "Electro House",
      "ダメージ": "40",
      "効果": "Your opponent’s Active Pokémon is now Poisoned.",
      "エネルギーコスト": 1,
      "エネルギータイプ": [
        "darkness"
      ]
    }
  ],
  "Alternate Arts": [],
  "進化先": {},
  "進化前": {
    "0": [
      [
        "Basic",
        "Poipole"
      ]
    ]
  }
}