{
  "カードの種類": "Pokémon",
  "カード番号": [
    "a3#217"
  ],
  "名前": "Blastoise",
  "レア度": {
    "rarity_types": [
      "shiny"
    ],
    "count": 1
  },
  "HP": "150",
  "タイプ": "water",
  "弱点": "lightning +20",
  "にげる": 3,
  "説明文": "It crushes its foe under its heavy body to cause fainting. In a pinch, it will withdraw inside its shell.",
  "イラストレーター": "Nisota Niso",
  "収録セット": [
    "Celestial Guardians"
  ],
  "入手方法": [
    "パック: Lunala Pack",
    "パック開封ポイント: 1000"
  ],
  "進化ステージ": "Stage 2",
  "特別ルール": null,
  "エフェクト一覧": [
    "Tiny_Twinkles_Flair_Yellow_Battle.webp",
    "Shiny_Sparkles_Flair_Battle.webp",
    "Small_Hexagons_Flair_Light_blue_Battle.webp",
    "Digital_Squares_Flair_Light_blue_Battle.webp"
  ],
  "特性": [],
  "ワザ": [
    {
      "名前": "Hydro Pump",
      "ダメージ": "80+",
      "効果": "If this Pokémon has at least 2 extra  Energy attached, this attack does 60 more damage.",
      "エネルギーコスト": 3,
      "エネルギータイプ": [
        "water",
        "water",
        "colorless"
      ]
    }
  ],
  "Alternate Arts": [
    {
      "カード番号": "a1#55"
    },
    {
      "カード番号": "promo-a#29"
    }
  ],
  "進化先": {},
  "進化前": {
    "0": [
      [
        "Stage 1",
        "Wartortle"
      ]
    ]
  }
}